Workbook

Sheet Risk Mgmt
A1: DBA4014 | C1: Risk Management Rules
A3: Company | B3: DBA4
A4: Date | B4: 46304 | D4: =IF(WEEKDAY(B4)=1,"SUN",IF(WEEKDAY(B4)=2,"MON",IF(WEEKDAY(B4)=3,"TUE",IF(WEEKDAY(B4)=4,"WED",IF(WEEKDAY(B4)=5,"THU",IF(WEEKDAY(B4)=6,"FRI",IF(WEEKDAY(B4)=7,"SAT","-")))))))
A5: Risk Management Rules (Self-Regulation)
A7: Loss-cut | B7: 10 | C7: % Enforcing this rule is primarily the CRO's responsibility. | N7: Our PaperTrade is limited to macro risks only - ETFs, ETNs, (i.e. ETPs) - Futures on indices and commodities - Options on indices and commodities - No investment in individual stocks No single-stock futures No single-stock options + No single-stock ETFs such as: (including but not limited to...) TSLQ: -1× the daily performance of Tesla NVDS: -1.25× the daily performance of Nvidia PYPS: -1.5× the daily performance of PayPal PYPT: +1.5× the daily performance of PayPal NKEQ: -2× the daily performance of Nike NKEL: +2× the daily performance of Nike PFES: -2× the daily performance of Pfizer PFEL: +2× the daily performance of Pfizer
A9: Profit-taking | B9: 15 | C9: % Enforcing this rule is primarily the CRO's responsibility.
B11: The "disposition effect": a behavioral bias
A13: Exposure Limits:
B14: Any one stock(ETF) exposure: | E14: 40 | F14: % of the fund (\10billion)
B15: Any one Country exposure: | E15: 80 | F15: % of the fund (\10billion)
B16: Any Futures Net exposure: | E16: 10 | F16: % of the fund (\10billion) | I16: size(exposure) = underlying asset's price x multiplier x #of contracts (x FX rate)
B17: Any Options Long exposure: | E17: 10 | F17: % of the fund (\10billion)
B18: Any Options Short exposure: | E18: 10 | F18: % of the fund (\10billion)
A20: New Trade | B20: Only on Friday at Friday's closing prices (Order-type: Market-on-Close)
A21: Trade Size | B21: Less than 25% of Daily Trading Volume on previous Thursday
A22: Leverage | B22: up to 30% of the asset at 3.64% p.a.
A23: ETF Borrowing | B23: up to 30% of the asset (at zero cost)
E24: NOTE: Each team should decide on its own limits.
A25: CEO | B25: 김경수
A26: CRO | B26: 박준형 | D26: Check if your orders are in compliance with your team's (self-imposing) risk management rules!
A27: CIO | B27: Jacob
A28: Research | B28: 장단비 | C28: 홍예나
A29: COO | B29: 채영찬
B32: If a loss-cut or profit-taking is triggered by your own conditions, (1) record the day's closing price & the day's FX rate, (2) notify your execution by email to yshin57@skku.edu on the same day, (3) apply the recorded price & FX rate on the valuation report (instead of applying the Friday's closing prices) | K32: 2026
K33: Valuation Report before 3pm on Monday | L33: Order Report before 3pm on Friday
L34: =B4 | M34: 0
J35: 0 | K35: =L34+3 | L35: =L34+7 | M35: 1
J36: 1 | K36: =L35+3 | L36: =L35+7 | M36: 2
J37: 2 | K37: =L36+3 | L37: =L36+7 | M37: 3
J38: 3 | K38: =L37+3 | L38: =L37+7 | M38: 4
J39: 4 | K39: =L38+3 | L39: =L38+7 | M39: 5
J40: 5 | K40: =L39+3 | L40: =L39+7 | M40: 6
J41: 6 | K41: =L40+3

Sheet 09-Oct
A1: ='Risk Mgmt'!A1 | D1: An Executive Summary for Investors: Strategy & Order(s) | J1: as of | K1: =TEXT(B4,"YYYY-MM-DD")
A3: Company | B3: ='Risk Mgmt'!B3 | F3: Loss-cut | G3: Profit-taking | H3: ETF | I3: Country | J3: Futures | K3: Options L | L3: Options S
A4: Date | B4: ='Risk Mgmt'!B4 | D4: =IF(WEEKDAY(B4)=1,"SUN",IF(WEEKDAY(B4)=2,"MON",IF(WEEKDAY(B4)=3,"TUE",IF(WEEKDAY(B4)=4,"WED",IF(WEEKDAY(B4)=5,"THU",IF(WEEKDAY(B4)=6,"FRI",IF(WEEKDAY(B4)=7,"SAT","-"))))))) | E4: before 3pm | F4: ='Risk Mgmt'!B7/100 | G4: ='Risk Mgmt'!B9/100 | H4: ='Risk Mgmt'!E14/100 | I4: ='Risk Mgmt'!E15/100 | J4: ='Risk Mgmt'!E16/100 | K4: ='Risk Mgmt'!E17/100 | L4: ='Risk Mgmt'!E18/100
E5: Important! No longer than 5 lines in each box. (Column width: 9, Font Size: 11, MS Clear Gothic) Line feed within a cell: Alt^Enter
N6: KRX-listed ETF code begins with letter A and ETN code begins with letter Q which prevent the codes from being read as numbers rather than text. US ETFs' codes are using 2 ~ 4 alphebet characters.
A7: Strategy | B7: Background | D7: 1 | E7: The investment objective is to achieve stable long-term capital appreciation through a diversified ETF portfolio.
D8: 2 | E8: Investment decisions are based on a predefined strategic asset allocation rather than short-term market timing.
D9: 3 | E9: The portfolio combines broad-market exposure, structural growth opportunities, and defensive investments.
D10: 4 | E10: The investment universe consists of Korea- and U.S.-listed ETFs, with an initial capital of KRW 10 billion.
D11: 5 | E11: This approach seeks to balance return potential and portfolio risk through diversification and disciplined risk management.
B12: Reasonings | D12: 1 | E12: The strategic allocation assigns 50% to core equity ETFs, 25% to growth-oriented ETFs, and 25% to defensive/value ETFs.
D13: 2 | E13: Core exposure is divided equally between the Korean and U.S. equity markets through KODEX 200 and SPY.
D14: 3 | E14: Growth exposure is allocated to semiconductor and cybersecurity ETFs to capture structural industry opportunities.
D15: 4 | E15: Defensive/value exposure combines short-term U.S. Treasury bills and dividend-oriented U.S. equities.
D16: 5 | E16: This allocation aims to diversify market and sector risks while maintaining exposure to long-term growth opportunities.
B17: Conclusions | D17: 1 | E17: For the first trading week, the team adopts the predetermined strategic allocation across six ETFs.
D18: 2 | E18: The portfolio allocates 25% to KODEX 200, 25% to SPY, 15% to SMH, and 10% to CIBR.
D19: 3 | E19: The remaining 25% is allocated to BIL (10%) and SCHD (15%) for defensive and dividend-oriented exposure.
D20: 4 | E20: All initial positions are established through buy orders using whole-share quantities and the applicable market closing prices.
D21: 5 | E21: Subsequent performance and risk exposure will be monitored through weekly portfolio valuation and team-approved risk management rules.
A23: MOC(Market-on-Close) Orders | E23: 1 | F23: 2 | G23: 3 | H23: 4 | I23: 5 | J23: 6 | K23: 7 | L23: 8
B24: Buy or Sell | E24: Buy | F24: Buy | G24: Buy | H24: Buy | I24: Buy | J24: Buy
A25: Product Name | E25: KODEX 200 | F25: SPDR S&P 500 ETF Trust | G25: VanEck Semiconductor ETF | H25: First Trust Nasdaq Cybersecurity ETF | I25: SPDR Bloomberg 1-3 Month T-Bill ETF | J25: Schwab U.S. Dividend Equity ETF
A26: Product Code | E26: A069500 | F26: SPY | G26: SMH | H26: CIBR | I26: BIL | J26: SCHD
A27: Product Type (ETF/Futures/Options) | E27: ETF | F27: ETF | G27: ETF | H27: ETF | I27: ETF | J27: ETF
A28: Size (shares, contracts) | E28: 23663 | F28: 2400 | G28: 1790 | H28: 7001 | I28: 8159 | J28: 34286
A29: Multiple (Futures&Options only) | E29: 1 | F29: 1 | G29: 1 | H29: 1 | I29: 1 | J29: 1
A30: Price | E30: 105650 | F30: Friday's closing Price | G30: Friday's closing Price | H30: Friday's closing Price | I30: Friday's closing Price | J30: Friday's closing Price | K30: Friday's closing Price | L30: Friday's closing Price
A31: FX (exchange rate) | E31: 1 | F31: Friday's closing FX rate | G31: Friday's closing FX rate | H31: Friday's closing FX rate | I31: Friday's closing FX rate | J31: Friday's closing FX rate | K31: Friday's closing FX rate | L31: Friday's closing FX rate
A32: Size Check | E32: =IF(E28=0,"",IF(E28<25%*E33,"OK","Too Big!")) | F32: =IF(F28=0,"",IF(F28<25%*F33,"OK","Too Big!")) | G32: =IF(G28=0,"",IF(G28<25%*G33,"OK","Too Big!")) | H32: =IF(H28=0,"",IF(H28<25%*H33,"OK","Too Big!")) | I32: =IF(I28=0,"",IF(I28<25%*I33,"OK","Too Big!")) | J32: =IF(J28=0,"",IF(J28<25%*J33,"OK","Too Big!")) | K32: =IF(K28=0,"",IF(K28<25%*K33,"OK","Too Big!")) | L32: =IF(L28=0,"",IF(L28<25%*L33,"OK","Too Big!"))
A33: Previous Thursday's daily trading volume (shares/contracts) | E33: 23139645 | F33: 34363355 | G33: 10886720 | H33: 1781429 | I33: 2951266 | J33: 23506901
A35: ='Risk Mgmt'!A25 | B35: ='Risk Mgmt'!B25 | E35: Adjust your order size to keep it smaller than a 25% of previous Thursday's trading volume of each interest.
A36: ='Risk Mgmt'!A26 | B36: ='Risk Mgmt'!B26 | C36: ='Risk Mgmt'!C26 | E36: [Normal Case] Total Investment < KRW 10 billion --> Remaining Cash Balance earns an interest of 0.035% per week. [Leverage Case] Total Investment > KRW 10 billion -->The amount over the budget (KRW 10 billion) incurs financing cost: 0.070% per week.
A37: ='Risk Mgmt'!A27 | B37: ='Risk Mgmt'!B27 | C37: ='Risk Mgmt'!C27
A38: ='Risk Mgmt'!A28 | B38: ='Risk Mgmt'!B28 | C38: ='Risk Mgmt'!C28
A39: ='Risk Mgmt'!A29 | B39: ='Risk Mgmt'!B29 | C39: ='Risk Mgmt'!C29 | E39: Check if your orders are in compliance with your team's (self-made) risk management rules!

Sheet 16-Oct
A1: ='Risk Mgmt'!A1 | D1: An Executive Summary for Investors: Strategy & Order(s) | J1: as of | K1: =TEXT(B4,"YYYY-MM-DD")
A3: Company | B3: ='Risk Mgmt'!B3 | F3: Loss-cut | G3: Profit-taking | H3: ETF | I3: Country | J3: Futures | K3: Options L | L3: Options S
A4: Date | B4: ='09-Oct'!B4+7 | D4: =IF(WEEKDAY(B4)=1,"SUN",IF(WEEKDAY(B4)=2,"MON",IF(WEEKDAY(B4)=3,"TUE",IF(WEEKDAY(B4)=4,"WED",IF(WEEKDAY(B4)=5,"THU",IF(WEEKDAY(B4)=6,"FRI",IF(WEEKDAY(B4)=7,"SAT","-"))))))) | E4: before 3pm | F4: ='09-Oct'!F4 | G4: ='09-Oct'!G4 | H4: ='09-Oct'!H4 | I4: ='09-Oct'!I4 | J4: ='09-Oct'!J4 | K4: ='09-Oct'!K4 | L4: ='09-Oct'!L4
E5: Important! No longer than 5 lines in each box. (Column width: 9, Font Size: 11, MS Clear Gothic) Line feed within a cell: Alt^Enter
N6: KRX-listed ETF code begins with letter A and ETN code begins with letter Q which prevent the codes from being read as numbers rather than text. US ETFs' codes are using 2 ~ 4 alphebet characters.
A7: Strategy | B7: Background | D7: 1 | E7: On Oct 15 the KOSPI fell 7.6% (circuit breaker, 7th straight loss); KOSPI200 lost 17.6% in a week. Drivers: doubts on AI-investment returns, Chinese memory supply (CXMT) and foreign selling of chips. U.S. September CPI rose 3.7% (core +0.3% m/m), lifting the odds of an October Fed hike to about 50%. Brent oil stayed above USD 100 on Middle East tensions; the U.S. dollar touched an 18-month high. U.S. large caps held up (S&P 500 about -1% in a week) while health care and staples sectors rose.
D8: 2
D9: 3
D10: 4
D11: 5
B12: Reasonings | D12: 1 | E12: Our -10% loss-cut on KODEX 200 is settled at the Oct 14 close (KRW 94,805), per your instruction. No re-entry into Korea this week: 20-day volatility of 44% would heavily penalize U = E(r) - 0.5*A*s^2. SMH and CIBR are near their loss-cut lines and share AI/tech risk, so we trim both to about 5% of NAV. XLV and XLP offer low volatility and positive momentum; XLE hedges inflation and oil-price risk. About 25% in KRW cash lowers portfolio volatility and funds a staged re-entry when conditions improve.
D13: 2
D14: 3
D15: 4
D16: 5
B17: Conclusions | D17: 1 | E17: Sell 1,151 SMH and 3,549 CIBR; buy 2,420 XLV, 3,298 XLP and 3,221 XLE shares at Friday's close (MOC). SPY, SCHD and BIL are unchanged; after the trades we hold 8 ETFs with about 25% in KRW cash. U.S. exposure is about 73% of the fund (limit 80%); largest ETF about 26% (limit 40%); no leverage/short. All order sizes are below 25% of Thursday's volume, and no single-stock products are used. We accept an underweight vs. the 40% KOSPI200 benchmark weight and will review re-entry on Oct 23.
D18: 2
D19: 3
D20: 4
D21: 5
A23: MOC(Market-on-Close) Orders | E23: 1 | F23: 2 | G23: 3 | H23: 4 | I23: 5 | J23: 6 | K23: 7 | L23: 8
B24: Buy or Sell | E24: Sell | F24: Sell | G24: Buy | H24: Buy | I24: Buy
A25: Product Name | E25: VanEck Semiconductor ETF | F25: First Trust Nasdaq Cybersecurity ETF | G25: State Street Health Care Select Sector SPDR ETF | H25: State Street Consumer Staples Select Sector SPDR ETF | I25: State Street Energy Select Sector SPDR ETF
A26: Product Code | E26: SMH | F26: CIBR | G26: XLV | H26: XLP | I26: XLE
A27: Product Type (ETF/Futures/Options) | E27: ETF | F27: ETF | G27: ETF | H27: ETF | I27: ETF
A28: Size (shares, contracts) | E28: 1151 | F28: 3549 | G28: 2420 | H28: 3298 | I28: 3221
A29: Multiple (Futures&Options only) | E29: 1 | F29: 1 | G29: 1 | H29: 1 | I29: 1
A30: Price | E30: Friday's closing Price | F30: Friday's closing Price | G30: Friday's closing Price | H30: Friday's closing Price | I30: Friday's closing Price | J30: Friday's closing Price | K30: Friday's closing Price | L30: Friday's closing Price
A31: FX (exchange rate) | E31: Friday's closing FX rate | F31: Friday's closing FX rate | G31: Friday's closing FX rate | H31: Friday's closing FX rate | I31: Friday's closing FX rate | J31: Friday's closing FX rate | K31: Friday's closing FX rate | L31: Friday's closing FX rate
A32: Size Check | E32: =IF(E28=0,"",IF(E28<25%*E33,"OK","Too Big!")) | F32: =IF(F28=0,"",IF(F28<25%*F33,"OK","Too Big!")) | G32: =IF(G28=0,"",IF(G28<25%*G33,"OK","Too Big!")) | H32: =IF(H28=0,"",IF(H28<25%*H33,"OK","Too Big!")) | I32: =IF(I28=0,"",IF(I28<25%*I33,"OK","Too Big!")) | J32: =IF(J28=0,"",IF(J28<25%*J33,"OK","Too Big!")) | K32: =IF(K28=0,"",IF(K28<25%*K33,"OK","Too Big!")) | L32: =IF(L28=0,"",IF(L28<25%*L33,"OK","Too Big!"))
A33: Previous Thursday's daily trading volume (shares/contracts) | E33: 14978200 | F33: 2789305 | G33: 11474100 | H33: 23971000 | I33: 31406300
A35: ='Risk Mgmt'!A25 | B35: ='Risk Mgmt'!B25 | E35: Adjust your order size to keep it smaller than a 25% of previous Thursday's trading volume of each interest.
A36: ='Risk Mgmt'!A26 | B36: ='Risk Mgmt'!B26 | C36: ='Risk Mgmt'!C26 | E36: [Normal Case] Total Investment < KRW 10 billion --> Remaining Cash Balance earns an interest of 0.035% per week. [Leverage Case] Total Investment > KRW 10 billion -->The amount over the budget (KRW 10 billion) incurs financing cost: 0.070% per week.
A37: ='Risk Mgmt'!A27 | B37: ='Risk Mgmt'!B27 | C37: ='Risk Mgmt'!C27
A38: ='Risk Mgmt'!A28 | B38: ='Risk Mgmt'!B28 | C38: ='Risk Mgmt'!C28
A39: ='Risk Mgmt'!A29 | B39: ='Risk Mgmt'!B29 | C39: ='Risk Mgmt'!C29 | E39: Check if your orders are in compliance with your team's (self-made) risk management rules!

Sheet 23-Oct
A1: ='Risk Mgmt'!A1 | D1: An Executive Summary for Investors: Strategy & Order(s) | J1: as of | K1: =TEXT(B4,"YYYY-MM-DD")
A3: Company | B3: ='Risk Mgmt'!B3 | F3: Loss-cut | G3: Profit-taking | H3: ETF | I3: Country | J3: Futures | K3: Options L | L3: Options S
A4: Date | B4: ='16-Oct'!B4+7 | D4: =IF(WEEKDAY(B4)=1,"SUN",IF(WEEKDAY(B4)=2,"MON",IF(WEEKDAY(B4)=3,"TUE",IF(WEEKDAY(B4)=4,"WED",IF(WEEKDAY(B4)=5,"THU",IF(WEEKDAY(B4)=6,"FRI",IF(WEEKDAY(B4)=7,"SAT","-"))))))) | E4: before 3pm | F4: ='16-Oct'!F4 | G4: ='16-Oct'!G4 | H4: ='16-Oct'!H4 | I4: ='16-Oct'!I4 | J4: ='16-Oct'!J4 | K4: ='16-Oct'!K4 | L4: ='16-Oct'!L4
E5: Important! No longer than 5 lines in each box. (Column width: 9, Font Size: 11, MS Clear Gothic) Line feed within a cell: Alt^Enter
N6: KRX-listed ETF code begins with letter A and ETN code begins with letter Q which prevent the codes from being read as numbers rather than text. US ETFs' codes are using 2 ~ 4 alphebet characters.
A7: Strategy | B7: Background | D7: 1
D8: 2
D9: 3
D10: 4
D11: 5
B12: Reasonings | D12: 1
D13: 2
D14: 3
D15: 4
D16: 5
B17: Conclusions | D17: 1
D18: 2
D19: 3
D20: 4
D21: 5
A23: MOC(Market-on-Close) Orders | E23: 1 | F23: 2 | G23: 3 | H23: 4 | I23: 5 | J23: 6 | K23: 7 | L23: 8
B24: Buy or Sell
A25: Product Name
A26: Product Code
A27: Product Type (ETF/Futures/Options)
A28: Size (shares, contracts)
A29: Multiple (Futures&Options only)
A30: Price | E30: Friday's closing Price | F30: Friday's closing Price | G30: Friday's closing Price | H30: Friday's closing Price | I30: Friday's closing Price | J30: Friday's closing Price | K30: Friday's closing Price | L30: Friday's closing Price
A31: FX (exchange rate) | E31: Friday's closing FX rate | F31: Friday's closing FX rate | G31: Friday's closing FX rate | H31: Friday's closing FX rate | I31: Friday's closing FX rate | J31: Friday's closing FX rate | K31: Friday's closing FX rate | L31: Friday's closing FX rate
A32: Size Check | E32: =IF(E28=0,"",IF(E28<25%*E33,"OK","Too Big!")) | F32: =IF(F28=0,"",IF(F28<25%*F33,"OK","Too Big!")) | G32: =IF(G28=0,"",IF(G28<25%*G33,"OK","Too Big!")) | H32: =IF(H28=0,"",IF(H28<25%*H33,"OK","Too Big!")) | I32: =IF(I28=0,"",IF(I28<25%*I33,"OK","Too Big!")) | J32: =IF(J28=0,"",IF(J28<25%*J33,"OK","Too Big!")) | K32: =IF(K28=0,"",IF(K28<25%*K33,"OK","Too Big!")) | L32: =IF(L28=0,"",IF(L28<25%*L33,"OK","Too Big!"))
A33: Previous Thursday's daily trading volume (shares/contracts)
A35: ='Risk Mgmt'!A25 | B35: ='Risk Mgmt'!B25 | E35: Adjust your order size to keep it smaller than a 25% of previous Thursday's trading volume of each interest.
A36: ='Risk Mgmt'!A26 | B36: ='Risk Mgmt'!B26 | C36: ='Risk Mgmt'!C26 | E36: [Normal Case] Total Investment < KRW 10 billion --> Remaining Cash Balance earns an interest of 0.035% per week. [Leverage Case] Total Investment > KRW 10 billion -->The amount over the budget (KRW 10 billion) incurs financing cost: 0.070% per week.
A37: ='Risk Mgmt'!A27 | B37: ='Risk Mgmt'!B27 | C37: ='Risk Mgmt'!C27
A38: ='Risk Mgmt'!A28 | B38: ='Risk Mgmt'!B28 | C38: ='Risk Mgmt'!C28
A39: ='Risk Mgmt'!A29 | B39: ='Risk Mgmt'!B29 | C39: ='Risk Mgmt'!C29 | E39: Check if your orders are in compliance with your team's (self-made) risk management rules!

Sheet 30-Oct
A1: ='Risk Mgmt'!A1 | D1: An Executive Summary for Investors: Strategy & Order(s) | J1: as of | K1: =TEXT(B4,"YYYY-MM-DD")
A3: Company | B3: ='Risk Mgmt'!B3 | F3: Loss-cut | G3: Profit-taking | H3: ETF | I3: Country | J3: Futures | K3: Options L | L3: Options S
A4: Date | B4: ='23-Oct'!B4+7 | D4: =IF(WEEKDAY(B4)=1,"SUN",IF(WEEKDAY(B4)=2,"MON",IF(WEEKDAY(B4)=3,"TUE",IF(WEEKDAY(B4)=4,"WED",IF(WEEKDAY(B4)=5,"THU",IF(WEEKDAY(B4)=6,"FRI",IF(WEEKDAY(B4)=7,"SAT","-"))))))) | E4: before 3pm | F4: ='23-Oct'!F4 | G4: ='23-Oct'!G4 | H4: ='23-Oct'!H4 | I4: ='23-Oct'!I4 | J4: ='23-Oct'!J4 | K4: ='23-Oct'!K4 | L4: ='23-Oct'!L4
E5: Important! No longer than 5 lines in each box. (Column width: 9, Font Size: 11, MS Clear Gothic) Line feed within a cell: Alt^Enter
N6: KRX-listed ETF code begins with letter A and ETN code begins with letter Q which prevent the codes from being read as numbers rather than text. US ETFs' codes are using 2 ~ 4 alphebet characters.
A7: Strategy | B7: Background | D7: 1
D8: 2
D9: 3
D10: 4
D11: 5
B12: Reasonings | D12: 1
D13: 2
D14: 3
D15: 4
D16: 5
B17: Conclusions | D17: 1
D18: 2
D19: 3
D20: 4
D21: 5
A23: MOC(Market-on-Close) Orders | E23: 1 | F23: 2 | G23: 3 | H23: 4 | I23: 5 | J23: 6 | K23: 7 | L23: 8
B24: Buy or Sell
A25: Product Name
A26: Product Code
A27: Product Type (ETF/Futures/Options)
A28: Size (shares, contracts)
A29: Multiple (Futures&Options only)
A30: Price | E30: Friday's closing Price | F30: Friday's closing Price | G30: Friday's closing Price | H30: Friday's closing Price | I30: Friday's closing Price | J30: Friday's closing Price | K30: Friday's closing Price | L30: Friday's closing Price
A31: FX (exchange rate) | E31: Friday's closing FX rate | F31: Friday's closing FX rate | G31: Friday's closing FX rate | H31: Friday's closing FX rate | I31: Friday's closing FX rate | J31: Friday's closing FX rate | K31: Friday's closing FX rate | L31: Friday's closing FX rate
A32: Size Check | E32: =IF(E28=0,"",IF(E28<25%*E33,"OK","Too Big!")) | F32: =IF(F28=0,"",IF(F28<25%*F33,"OK","Too Big!")) | G32: =IF(G28=0,"",IF(G28<25%*G33,"OK","Too Big!")) | H32: =IF(H28=0,"",IF(H28<25%*H33,"OK","Too Big!")) | I32: =IF(I28=0,"",IF(I28<25%*I33,"OK","Too Big!")) | J32: =IF(J28=0,"",IF(J28<25%*J33,"OK","Too Big!")) | K32: =IF(K28=0,"",IF(K28<25%*K33,"OK","Too Big!")) | L32: =IF(L28=0,"",IF(L28<25%*L33,"OK","Too Big!"))
A33: Previous Thursday's daily trading volume (shares/contracts)
A35: ='Risk Mgmt'!A25 | B35: ='Risk Mgmt'!B25 | E35: Adjust your order size to keep it smaller than a 25% of previous Thursday's trading volume of each interest.
A36: ='Risk Mgmt'!A26 | B36: ='Risk Mgmt'!B26 | C36: ='Risk Mgmt'!C26 | E36: [Normal Case] Total Investment < KRW 10 billion --> Remaining Cash Balance earns an interest of 0.035% per week. [Leverage Case] Total Investment > KRW 10 billion -->The amount over the budget (KRW 10 billion) incurs financing cost: 0.070% per week.
A37: ='Risk Mgmt'!A27 | B37: ='Risk Mgmt'!B27 | C37: ='Risk Mgmt'!C27
A38: ='Risk Mgmt'!A28 | B38: ='Risk Mgmt'!B28 | C38: ='Risk Mgmt'!C28
A39: ='Risk Mgmt'!A29 | B39: ='Risk Mgmt'!B29 | C39: ='Risk Mgmt'!C29 | E39: Check if your orders are in compliance with your team's (self-made) risk management rules!

Sheet 06-Nov
A1: ='Risk Mgmt'!A1 | D1: An Executive Summary for Investors: Strategy & Order(s) | J1: as of | K1: =TEXT(B4,"YYYY-MM-DD")
A3: Company | B3: ='Risk Mgmt'!B3 | F3: Loss-cut | G3: Profit-taking | H3: ETF | I3: Country | J3: Futures | K3: Options L | L3: Options S
A4: Date | B4: ='30-Oct'!B4+7 | D4: =IF(WEEKDAY(B4)=1,"SUN",IF(WEEKDAY(B4)=2,"MON",IF(WEEKDAY(B4)=3,"TUE",IF(WEEKDAY(B4)=4,"WED",IF(WEEKDAY(B4)=5,"THU",IF(WEEKDAY(B4)=6,"FRI",IF(WEEKDAY(B4)=7,"SAT","-"))))))) | E4: before 3pm | F4: ='30-Oct'!F4 | G4: ='30-Oct'!G4 | H4: ='30-Oct'!H4 | I4: ='30-Oct'!I4 | J4: ='30-Oct'!J4 | K4: ='30-Oct'!K4 | L4: ='30-Oct'!L4
E5: Important! No longer than 5 lines in each box. (Column width: 9, Font Size: 11, MS Clear Gothic) Line feed within a cell: Alt^Enter
N6: KRX-listed ETF code begins with letter A and ETN code begins with letter Q which prevent the codes from being read as numbers rather than text. US ETFs' codes are using 2 ~ 4 alphebet characters.
A7: Strategy | B7: Background | D7: 1
D8: 2
D9: 3
D10: 4
D11: 5
B12: Reasonings | D12: 1
D13: 2
D14: 3
D15: 4
D16: 5
B17: Conclusions | D17: 1
D18: 2
D19: 3
D20: 4
D21: 5
A23: MOC(Market-on-Close) Orders | E23: 1 | F23: 2 | G23: 3 | H23: 4 | I23: 5 | J23: 6 | K23: 7 | L23: 8
B24: Buy or Sell
A25: Product Name
A26: Product Code
A27: Product Type (ETF/Futures/Options)
A28: Size (shares, contracts)
A29: Multiple (Futures&Options only)
A30: Price | E30: Friday's closing Price | F30: Friday's closing Price | G30: Friday's closing Price | H30: Friday's closing Price | I30: Friday's closing Price | J30: Friday's closing Price | K30: Friday's closing Price | L30: Friday's closing Price
A31: FX (exchange rate) | E31: Friday's closing FX rate | F31: Friday's closing FX rate | G31: Friday's closing FX rate | H31: Friday's closing FX rate | I31: Friday's closing FX rate | J31: Friday's closing FX rate | K31: Friday's closing FX rate | L31: Friday's closing FX rate
A32: Size Check | E32: =IF(E28=0,"",IF(E28<25%*E33,"OK","Too Big!")) | F32: =IF(F28=0,"",IF(F28<25%*F33,"OK","Too Big!")) | G32: =IF(G28=0,"",IF(G28<25%*G33,"OK","Too Big!")) | H32: =IF(H28=0,"",IF(H28<25%*H33,"OK","Too Big!")) | I32: =IF(I28=0,"",IF(I28<25%*I33,"OK","Too Big!")) | J32: =IF(J28=0,"",IF(J28<25%*J33,"OK","Too Big!")) | K32: =IF(K28=0,"",IF(K28<25%*K33,"OK","Too Big!")) | L32: =IF(L28=0,"",IF(L28<25%*L33,"OK","Too Big!"))
A33: Previous Thursday's daily trading volume (shares/contracts)
A35: ='Risk Mgmt'!A25 | B35: ='Risk Mgmt'!B25 | E35: Adjust your order size to keep it smaller than a 25% of previous Thursday's trading volume of each interest.
A36: ='Risk Mgmt'!A26 | B36: ='Risk Mgmt'!B26 | C36: ='Risk Mgmt'!C26 | E36: [Normal Case] Total Investment < KRW 10 billion --> Remaining Cash Balance earns an interest of 0.035% per week. [Leverage Case] Total Investment > KRW 10 billion -->The amount over the budget (KRW 10 billion) incurs financing cost: 0.070% per week.
A37: ='Risk Mgmt'!A27 | B37: ='Risk Mgmt'!B27 | C37: ='Risk Mgmt'!C27
A38: ='Risk Mgmt'!A28 | B38: ='Risk Mgmt'!B28 | C38: ='Risk Mgmt'!C28
A39: ='Risk Mgmt'!A29 | B39: ='Risk Mgmt'!B29 | C39: ='Risk Mgmt'!C29 | E39: Check if your orders are in compliance with your team's (self-made) risk management rules!

Sheet 13-Nov
A1: ='Risk Mgmt'!A1 | D1: An Executive Summary for Investors: Strategy & Order(s) | J1: as of | K1: =TEXT(B4,"YYYY-MM-DD")
A3: Company | B3: ='Risk Mgmt'!B3 | F3: Loss-cut | G3: Profit-taking | H3: ETF | I3: Country | J3: Futures | K3: Options L | L3: Options S
A4: Date | B4: ='06-Nov'!B4+7 | D4: =IF(WEEKDAY(B4)=1,"SUN",IF(WEEKDAY(B4)=2,"MON",IF(WEEKDAY(B4)=3,"TUE",IF(WEEKDAY(B4)=4,"WED",IF(WEEKDAY(B4)=5,"THU",IF(WEEKDAY(B4)=6,"FRI",IF(WEEKDAY(B4)=7,"SAT","-"))))))) | E4: before 3pm | F4: ='06-Nov'!F4 | G4: ='06-Nov'!G4 | H4: ='06-Nov'!H4 | I4: ='06-Nov'!I4 | J4: ='06-Nov'!J4 | K4: ='06-Nov'!K4 | L4: ='06-Nov'!L4
E5: Important! No longer than 5 lines in each box. (Column width: 9, Font Size: 11, MS Clear Gothic) Line feed within a cell: Alt^Enter
N6: KRX-listed ETF code begins with letter A and ETN code begins with letter Q which prevent the codes from being read as numbers rather than text. US ETFs' codes are using 2 ~ 4 alphebet characters.
A7: Strategy | B7: Background | D7: 1
D8: 2
D9: 3
D10: 4
D11: 5
B12: Reasonings | D12: 1
D13: 2
D14: 3
D15: 4
D16: 5
B17: Conclusions | D17: 1
D18: 2
D19: 3
D20: 4
D21: 5
A23: MOC(Market-on-Close) Orders | E23: 1 | F23: 2 | G23: 3 | H23: 4 | I23: 5 | J23: 6 | K23: 7 | L23: 8
B24: Buy or Sell
A25: Product Name
A26: Product Code
A27: Product Type (ETF/Futures/Options)
A28: Size (shares, contracts)
A29: Multiple (Futures&Options only)
A30: Price | E30: Friday's closing Price | F30: Friday's closing Price | G30: Friday's closing Price | H30: Friday's closing Price | I30: Friday's closing Price | J30: Friday's closing Price | K30: Friday's closing Price | L30: Friday's closing Price
A31: FX (exchange rate) | E31: Friday's closing FX rate | F31: Friday's closing FX rate | G31: Friday's closing FX rate | H31: Friday's closing FX rate | I31: Friday's closing FX rate | J31: Friday's closing FX rate | K31: Friday's closing FX rate | L31: Friday's closing FX rate
A32: Size Check | E32: =IF(E28=0,"",IF(E28<25%*E33,"OK","Too Big!")) | F32: =IF(F28=0,"",IF(F28<25%*F33,"OK","Too Big!")) | G32: =IF(G28=0,"",IF(G28<25%*G33,"OK","Too Big!")) | H32: =IF(H28=0,"",IF(H28<25%*H33,"OK","Too Big!")) | I32: =IF(I28=0,"",IF(I28<25%*I33,"OK","Too Big!")) | J32: =IF(J28=0,"",IF(J28<25%*J33,"OK","Too Big!")) | K32: =IF(K28=0,"",IF(K28<25%*K33,"OK","Too Big!")) | L32: =IF(L28=0,"",IF(L28<25%*L33,"OK","Too Big!"))
A33: Previous Thursday's daily trading volume (shares/contracts)
A35: ='Risk Mgmt'!A25 | B35: ='Risk Mgmt'!B25 | E35: Adjust your order size to keep it smaller than a 25% of previous Thursday's trading volume of each interest.
A36: ='Risk Mgmt'!A26 | B36: ='Risk Mgmt'!B26 | C36: ='Risk Mgmt'!C26 | E36: [Normal Case] Total Investment < KRW 10 billion --> Remaining Cash Balance earns an interest of 0.035% per week. [Leverage Case] Total Investment > KRW 10 billion -->The amount over the budget (KRW 10 billion) incurs financing cost: 0.070% per week.
A37: ='Risk Mgmt'!A27 | B37: ='Risk Mgmt'!B27 | C37: ='Risk Mgmt'!C27
A38: ='Risk Mgmt'!A28 | B38: ='Risk Mgmt'!B28 | C38: ='Risk Mgmt'!C28
A39: ='Risk Mgmt'!A29 | B39: ='Risk Mgmt'!B29 | C39: ='Risk Mgmt'!C29 | E39: Check if your orders are in compliance with your team's (self-made) risk management rules!

Sheet 20-Nov
A1: ='Risk Mgmt'!A1 | D1: An Executive Summary for Investors: Strategy & Order(s) | J1: as of | K1: =TEXT(B4,"YYYY-MM-DD")
A3: Company | B3: ='Risk Mgmt'!B3 | F3: Loss-cut | G3: Profit-taking | H3: ETF | I3: Country | J3: Futures | K3: Options L | L3: Options S
A4: Date | B4: ='13-Nov'!B4+7 | D4: =IF(WEEKDAY(B4)=1,"SUN",IF(WEEKDAY(B4)=2,"MON",IF(WEEKDAY(B4)=3,"TUE",IF(WEEKDAY(B4)=4,"WED",IF(WEEKDAY(B4)=5,"THU",IF(WEEKDAY(B4)=6,"FRI",IF(WEEKDAY(B4)=7,"SAT","-"))))))) | E4: before 3pm | F4: ='13-Nov'!F4 | G4: ='13-Nov'!G4 | H4: ='13-Nov'!H4 | I4: ='13-Nov'!I4 | J4: ='13-Nov'!J4 | K4: ='13-Nov'!K4 | L4: ='13-Nov'!L4
E5: Important! No longer than 5 lines in each box. (Column width: 9, Font Size: 11, MS Clear Gothic) Line feed within a cell: Alt^Enter
N6: KRX-listed ETF code begins with letter A and ETN code begins with letter Q which prevent the codes from being read as numbers rather than text. US ETFs' codes are using 2 ~ 4 alphebet characters.
A7: Strategy | B7: Background | D7: 1 | E7: Back to Cash(KRW): Close all positions on risky assets. 1. If the trading volume of a particular asset is not big enough to reflect your liquidation, the liquidation could be split into smaller portions, e.g. 1/3 at Wednesday close, 1/3 at Thursday close and 1/3 at Friday close. 2. Liquidation of a long position of American-style option (e.g. ETF options) is done by simply exercising the right to buy the underlying asset at the strike price. (Apply cash-settlement for return calc.) 3. Liquidation of a long position of European-style option should be done by selling at the market(exchange). [Liquidation of a short position of European & American-style option should be done by buying back at the market(exchange).] 4. Kospi200 Index Options expire on the 2nd Thursday of every maturity month.
D8: 2
D9: 3
D10: 4
D11: 5
B12: Reasonings | D12: 1
D13: 2
D14: 3
D15: 4
D16: 5
B17: Conclusions | D17: 1
D18: 2
D19: 3
D20: 4
D21: 5
A23: MOC(Market-on-Close) Orders | E23: 1 | F23: 2 | G23: 3 | H23: 4 | I23: 5 | J23: 6 | K23: 7 | L23: 8
B24: Buy or Sell
A25: Product Name
A26: Product Code
A27: Product Type (ETF/Futures/Options)
A28: Size (shares, contracts)
A29: Multiple (Futures&Options only)
A30: Price | E30: Friday's closing Price | F30: Friday's closing Price | G30: Friday's closing Price | H30: Friday's closing Price | I30: Friday's closing Price | J30: Friday's closing Price | K30: Friday's closing Price | L30: Friday's closing Price
A31: FX (exchange rate) | E31: Friday's closing FX rate | F31: Friday's closing FX rate | G31: Friday's closing FX rate | H31: Friday's closing FX rate | I31: Friday's closing FX rate | J31: Friday's closing FX rate | K31: Friday's closing FX rate | L31: Friday's closing FX rate
A32: Size Check | E32: =IF(E28=0,"",IF(E28<25%*E33,"OK","Too Big!")) | F32: =IF(F28=0,"",IF(F28<25%*F33,"OK","Too Big!")) | G32: =IF(G28=0,"",IF(G28<25%*G33,"OK","Too Big!")) | H32: =IF(H28=0,"",IF(H28<25%*H33,"OK","Too Big!")) | I32: =IF(I28=0,"",IF(I28<25%*I33,"OK","Too Big!")) | J32: =IF(J28=0,"",IF(J28<25%*J33,"OK","Too Big!")) | K32: =IF(K28=0,"",IF(K28<25%*K33,"OK","Too Big!")) | L32: =IF(L28=0,"",IF(L28<25%*L33,"OK","Too Big!"))
A33: Previous Thursday's daily trading volume (shares/contracts)
A35: ='Risk Mgmt'!A25 | B35: ='Risk Mgmt'!B25 | E35: Adjust your order size to keep it smaller than a 25% of previous Thursday's trading volume of each interest.
A36: ='Risk Mgmt'!A26 | B36: ='Risk Mgmt'!B26 | C36: ='Risk Mgmt'!C26 | E36: [Normal Case] Total Investment < KRW 10 billion --> Remaining Cash Balance earns an interest of 0.035% per week. [Leverage Case] Total Investment > KRW 10 billion -->The amount over the budget (KRW 10 billion) incurs financing cost: 0.070% per week.
A37: ='Risk Mgmt'!A27 | B37: ='Risk Mgmt'!B27 | C37: ='Risk Mgmt'!C27
A38: ='Risk Mgmt'!A28 | B38: ='Risk Mgmt'!B28 | C38: ='Risk Mgmt'!C28
A39: ='Risk Mgmt'!A29 | B39: ='Risk Mgmt'!B29 | C39: ='Risk Mgmt'!C29
